posttroll/__init__.py
posttroll/address_receiver.py
posttroll/bbmcast.py
posttroll/listener.py
posttroll/logger.py
posttroll/message.py
posttroll/message_broadcaster.py
posttroll/ns.py
posttroll/publisher.py
posttroll/subscriber.py
posttroll/testing.py
posttroll/version.py
posttroll/backends/__init__.py
posttroll/backends/zmq/__init__.py
posttroll/backends/zmq/address_receiver.py
posttroll/backends/zmq/message_broadcaster.py
posttroll/backends/zmq/ns.py
posttroll/backends/zmq/publisher.py
posttroll/backends/zmq/socket.py
posttroll/backends/zmq/subscriber.py
posttroll/tests/__init__.py
posttroll/tests/conftest.py
posttroll/tests/test_bbmcast.py
posttroll/tests/test_message.py
posttroll/tests/test_nameserver.py
posttroll/tests/test_pubsub.py
posttroll/tests/test_secure_zmq_backend.py
posttroll/tests/test_testing.py
posttroll/tests/test_unsecure_zmq_backend.py
posttroll/tests/data/message_metadata.dumps.simplejson
posttroll/tests/data/message_metadata_aware.dumps
posttroll/tests/data/message_metadata_unaware.dumps
posttroll-1.13.1.dist-info/METADATA
posttroll-1.13.1.dist-info/WHEEL
posttroll-1.13.1.dist-info/entry_points.txt
posttroll-1.13.1.dist-info/licenses/LICENSE.txt
posttroll-1.13.1.dist-info/RECORD
